bytehouse_driver/__init__.py
bytehouse_driver/block.py
bytehouse_driver/blockstreamprofileinfo.py
bytehouse_driver/bufferedreader.cpython-310-darwin.so
bytehouse_driver/bufferedwriter.cpython-310-darwin.so
bytehouse_driver/client.py
bytehouse_driver/clientinfo.py
bytehouse_driver/connection.py
bytehouse_driver/context.py
bytehouse_driver/defines.py
bytehouse_driver/errors.py
bytehouse_driver/log.py
bytehouse_driver/opentelemetry.py
bytehouse_driver/progress.py
bytehouse_driver/protocol.py
bytehouse_driver/queryprocessingstage.py
bytehouse_driver/reader.py
bytehouse_driver/readhelpers.py
bytehouse_driver/result.py
bytehouse_driver/varint.cpython-310-darwin.so
bytehouse_driver/writer.py
bytehouse_driver/columns/__init__.py
bytehouse_driver/columns/arraycolumn.py
bytehouse_driver/columns/base.py
bytehouse_driver/columns/datecolumn.py
bytehouse_driver/columns/datetimecolumn.py
bytehouse_driver/columns/decimalcolumn.py
bytehouse_driver/columns/enumcolumn.py
bytehouse_driver/columns/exceptions.py
bytehouse_driver/columns/floatcolumn.py
bytehouse_driver/columns/intcolumn.py
bytehouse_driver/columns/intervalcolumn.py
bytehouse_driver/columns/ipcolumn.py
bytehouse_driver/columns/largeint.cpython-310-darwin.so
bytehouse_driver/columns/lowcardinalitycolumn.py
bytehouse_driver/columns/mapcolumn.py
bytehouse_driver/columns/nestedcolumn.py
bytehouse_driver/columns/nothingcolumn.py
bytehouse_driver/columns/nullablecolumn.py
bytehouse_driver/columns/nullcolumn.py
bytehouse_driver/columns/service.py
bytehouse_driver/columns/simpleaggregatefunctioncolumn.py
bytehouse_driver/columns/stringcolumn.py
bytehouse_driver/columns/tuplecolumn.py
bytehouse_driver/columns/util.py
bytehouse_driver/columns/uuidcolumn.py
bytehouse_driver/columns/numpy/__init__.py
bytehouse_driver/columns/numpy/base.py
bytehouse_driver/columns/numpy/datecolumn.py
bytehouse_driver/columns/numpy/datetimecolumn.py
bytehouse_driver/columns/numpy/floatcolumn.py
bytehouse_driver/columns/numpy/intcolumn.py
bytehouse_driver-1.0.5.dist-info/licenses/LICENSE
bytehouse_driver-1.0.5.dist-info/METADATA
bytehouse_driver-1.0.5.dist-info/WHEEL
bytehouse_driver-1.0.5.dist-info/top_level.txt
bytehouse_driver-1.0.5.dist-info/RECORD
